{
  "success": true,
  "data": {
    "pageInfo": {
      "totalPages": 93,
      "currentPage": 23,
      "hasNextPage": true
    },
    "response": [
      {
        "title": "Tiger & Bunny 2",
        "alternativeTitle": "Tiger & Bunny 2",
        "id": "tiger-bunny-2-15580",
        "poster": "https://cdn.noitatnemucod.net/thumbnail/300x400/100/897c82bfa04ce2ce12df353cc02e5b02.jpg",
        "episodes": {
          "sub": 13,
          "dub": 13,
          "eps": 13
        },
        "type": "TV",
        "duration": "25m"
      },
      {
        "title": "Tian Guan Ci Fu",
        "alternativeTitle": "Tian Guan Ci Fu",
        "id": "tian-guan-ci-fu-15579",
        "poster": "https://cdn.noitatnemucod.net/thumbnail/300x400/100/9209135e301a83da469922151d369f53.jpg",
        "episodes": {
          "sub": 11,
          "dub": 11,
          "eps": 11
        },
        "type": "ONA",
        "duration": "25m"
      },
      {
        "title": "The Slime Diaries: That Time I Got Reincarnated as a Slime",
        "alternativeTitle": "Tensura Nikki: Tensei shitara Slime Datta Ken",
        "id": "the-slime-diaries-that-time-i-got-reincarnated-as-a-slime-15577",
        "poster": "https://cdn.noitatnemucod.net/thumbnail/300x400/100/3dc0ccc5096044cc205d88d48ca337df.jpg",
        "episodes": {
          "sub": 12,
          "dub": 12,
          "eps": 12
        },
        "type": "TV",
        "duration": "23m"
      },
      {
        "title": "That Time I Got Reincarnated as a Slime 2nd Season Part 2",
        "alternativeTitle": "Tensei shitara Slime Datta Ken 2nd Season Part 2",
        "id": "that-time-i-got-reincarnated-as-a-slime-2nd-season-part-2-15576",
        "poster": "https://cdn.noitatnemucod.net/thumbnail/300x400/100/e68f6d1a80303c65d654d94d2d71e1e0.jpg",
        "episodes": {
          "sub": 12,
          "dub": 12,
          "eps": 12
        },
        "type": "TV",
        "duration": "22m"
      },
      {
        "title": "That Time I Got Reincarnated as a Slime Season 2",
        "alternativeTitle": "Tensei shitara Slime Datta Ken 2nd Season",
        "id": "that-time-i-got-reincarnated-as-a-slime-season-2-15575",
        "poster": "https://cdn.noitatnemucod.net/thumbnail/300x400/100/75a23fa4eb94eee8d8e9b973915052af.jpg",
        "episodes": {
          "sub": 12,
          "dub": 12,
          "eps": 12
        },
        "type": "TV",
        "duration": "23m"
      },
      {
        "title": "Suppose a Kid from the Last Dungeon Boonies moved to a starter town?",
        "alternativeTitle": "Tatoeba Last Dungeon Mae no Mura no Shounen ga Joban no Machi de Kurasu Youna Monogatari",
        "id": "suppose-a-kid-from-the-last-dungeon-boonies-moved-to-a-starter-town-15572",
        "poster": "https://cdn.noitatnemucod.net/thumbnail/300x400/100/fe5a936dab12028964d437b5fc8789e4.jpg",
        "episodes": {
          "sub": 12,
          "dub": 12,
          "eps": 12
        },
        "type": "TV",
        "duration": "24m"
      },
      {
        "title": "The Rising of the Shield Hero Season 3",
        "alternativeTitle": "Tate no Yuusha no Nariagari Season 3",
        "id": "the-rising-of-the-shield-hero-season-3-15571",
        "poster": "https://cdn.noitatnemucod.net/thumbnail/300x400/100/17e74704002aeb5bcec7e191c57b790b.jpg",
        "episodes": {
          "sub": 12,
          "dub": 12,
          "eps": 12
        },
        "type": "TV",
        "duration": "24m"
      },
      {
        "title": "The Rising of the Shield Hero 2nd Season",
        "alternativeTitle": "Tate no Yuusha no Nariagari Season 2",
        "id": "the-rising-of-the-shield-hero-2nd-season-15570",
        "poster": "https://cdn.noitatnemucod.net/thumbnail/300x400/100/fffadff17fe026c2031fb44ff5d70175.png",
        "episodes": {
          "sub": 13,
          "dub": 13,
          "eps": 13
        },
        "type": "TV",
        "duration": "24m"
      },
      {
        "title": "Taiso Samurai",
        "alternativeTitle": "Taisou Zamurai",
        "id": "taiso-samurai-15569",
        "poster": "https://cdn.noitatnemucod.net/thumbnail/300x400/100/09d4e41955fec78bf5548b989fbcfdff.jpg",
        "episodes": {
          "sub": 11,
          "dub": 11,
          "eps": 11
        },
        "type": "TV",
        "duration": "23m"
      },
      {
        "title": "Sword Art Online: Progressive",
        "alternativeTitle": "Sword Art Online: Progressive Movie - Hoshi Naki Yoru no Aria",
        "id": "sword-art-online-progressive-15568",
        "poster": "https://cdn.noitatnemucod.net/thumbnail/300x400/100/d90056d307fb7c0a71edec939d4a6266.jpg",
        "episodes": {
          "sub": 1,
          "dub": 1,
          "eps": 1
        },
        "type": "Movie",
        "duration": "97m"
      },
      {
        "title": "Super Cub",
        "alternativeTitle": "Super Cub",
        "id": "super-cub-15567",
        "poster": "https://cdn.noitatnemucod.net/thumbnail/300x400/100/d94ccadef64a5ef06b4813b3c9207d18.jpg",
        "episodes": {
          "sub": 12,
          "dub": 12,
          "eps": 12
        },
        "type": "TV",
        "duration": "24m"
      },
      {
        "title": "The World Ends with You The Animation",
        "alternativeTitle": "Subarashiki Kono Sekai The Animation",
        "id": "the-world-ends-with-you-the-animation-15566",
        "poster": "https://cdn.noitatnemucod.net/thumbnail/300x400/100/b49331f51e585dfdfe51ff8683be0d63.png",
        "episodes": {
          "sub": 12,
          "dub": 12,
          "eps": 12
        },
        "type": "TV",
        "duration": "24m"
      },
      {
        "title": "SSSS.Dynazenon",
        "alternativeTitle": "SSSS.Dynazenon",
        "id": "ssssdynazenon-15563",
        "poster": "https://cdn.noitatnemucod.net/thumbnail/300x400/100/8d744829666ceda17408d9184f299847.jpg",
        "episodes": {
          "sub": 12,
          "dub": 12,
          "eps": 12
        },
        "type": "TV",
        "duration": "23m"
      },
      {
        "title": "Spriggan (ONA)",
        "alternativeTitle": "Spriggan (ONA)",
        "id": "spriggan-ona-15562",
        "poster": "https://cdn.noitatnemucod.net/thumbnail/300x400/100/3b03461937f3fce0ab679004983c0b16.jpg",
        "episodes": {
          "sub": 6,
          "dub": 6,
          "eps": 6
        },
        "type": "ONA",
        "duration": "45m"
      },
      {
        "title": "LBX Girls",
        "alternativeTitle": "Soukou Musume Senki",
        "id": "lbx-girls-15560",
        "poster": "https://cdn.noitatnemucod.net/thumbnail/300x400/100/00ba6901cb21416a6d76e7a325f2dc68.jpg",
        "episodes": {
          "sub": 12,
          "dub": 12,
          "eps": 12
        },
        "type": "TV",
        "duration": "23m"
      },
      {
        "title": "Sore Ike! Anpanman: Fuwa Fuwa Fuwaly to Kumo no Kuni",
        "alternativeTitle": "Sore Ike! Anpanman: Fuwa Fuwa Fuwaly to Kumo no Kuni",
        "id": "sore-ike-anpanman-fuwa-fuwa-fuwaly-to-kumo-no-kuni-15559",
        "poster": "https://cdn.noitatnemucod.net/thumbnail/300x400/100/15dbb67bbda0a038760f6734d917c952.jpg",
        "episodes": {
          "sub": 0,
          "dub": 1,
          "eps": 0
        },
        "type": "Movie",
        "duration": "62m"
      },
      {
        "title": "I've Been Killing Slimes for 300 Years and Maxed Out My Level",
        "alternativeTitle": "Slime Taoshite 300-nen, Shiranai Uchi ni Level Max ni Nattemashita",
        "id": "ive-been-killing-slimes-for-300-years-and-maxed-out-my-level-15557",
        "poster": "https://cdn.noitatnemucod.net/thumbnail/300x400/100/d75b2c818c650c8ff1468a5017c4e5e8.jpg",
        "episodes": {
          "sub": 12,
          "dub": 12,
          "eps": 12
        },
        "type": "TV",
        "duration": "25m"
      },
      {
        "title": "SK8 the Infinity",
        "alternativeTitle": "SK∞",
        "id": "sk8-the-infinity-15556",
        "poster": "https://cdn.noitatnemucod.net/thumbnail/300x400/100/81b54f6b3b5fa0767ae06ad39668eae8.jpg",
        "episodes": {
          "sub": 12,
          "dub": 12,
          "eps": 12
        },
        "type": "TV",
        "duration": "23m"
      },
      {
        "title": "Skate-Leading☆Stars",
        "alternativeTitle": "Skate-Leading☆Stars",
        "id": "skate-leadingstars-15555",
        "poster": "https://cdn.noitatnemucod.net/thumbnail/300x400/100/ef91377db7bb377d807e95b8b568b60e.jpg",
        "episodes": {
          "sub": 12,
          "dub": 12,
          "eps": 12
        },
        "type": "TV",
        "duration": "23m"
      },
      {
        "title": "Show by Rock!! Stars!!",
        "alternativeTitle": "Show by Rock!! Stars!!",
        "id": "show-by-rock-stars-15552",
        "poster": "https://cdn.noitatnemucod.net/thumbnail/300x400/100/bc065259bd3424cd4827e62c107f1379.jpg",
        "episodes": {
          "sub": 12,
          "dub": 12,
          "eps": 12
        },
        "type": "TV",
        "duration": "23m"
      },
      {
        "title": "Attack on Titan: Final Season, Part 1",
        "alternativeTitle": "Shingeki no Kyojin: Final Season, Part 1",
        "id": "attack-on-titan-final-season-part-1-15548",
        "poster": "https://cdn.noitatnemucod.net/thumbnail/300x400/100/83da53919d7a20332be01686141f18f6.jpg",
        "episodes": {
          "sub": 16,
          "dub": 16,
          "eps": 16
        },
        "type": "TV",
        "duration": "23m"
      },
      {
        "title": "The New Prince of Tennis: Hyoutei vs. Rikkai - Game of Future",
        "alternativeTitle": "Shin Tennis no Ouji-sama: Hyoutei vs. Rikkai - Game of Future",
        "id": "the-new-prince-of-tennis-hyoutei-vs-rikkai-game-of-future-15547",
        "poster": "https://cdn.noitatnemucod.net/thumbnail/300x400/100/f538794ec61cd267f24563059161e657.jpg",
        "episodes": {
          "sub": 2,
          "dub": 2,
          "eps": 2
        },
        "type": "ONA",
        "duration": "48m"
      },
      {
        "title": "Shikizakura",
        "alternativeTitle": "Shikizakura",
        "id": "shikizakura-15545",
        "poster": "https://cdn.noitatnemucod.net/thumbnail/300x400/100/4f1cf149ca8a9cf8b91030ff359f751b.jpg",
        "episodes": {
          "sub": 12,
          "dub": 12,
          "eps": 12
        },
        "type": "TV",
        "duration": "24m"
      },
      {
        "title": "Shika no Ou",
        "alternativeTitle": "Shika no Ou",
        "id": "shika-no-ou-15544",
        "poster": "https://cdn.noitatnemucod.net/thumbnail/300x400/100/95f7f3980fe3dda8c98691857416b56d.jpg",
        "episodes": {
          "sub": 1,
          "dub": 1,
          "eps": 1
        },
        "type": "Movie",
        "duration": "114m"
      },
      {
        "title": "Shaman King (2021)",
        "alternativeTitle": "Shaman King (2021)",
        "id": "shaman-king-2021-15541",
        "poster": "https://cdn.noitatnemucod.net/thumbnail/300x400/100/b8e8ab94a56f1e3eb720f1b218ba1c4c.jpg",
        "episodes": {
          "sub": 52,
          "dub": 52,
          "eps": 52
        },
        "type": "TV",
        "duration": "23m"
      },
      {
        "title": "Combatants Will Be Dispatched!",
        "alternativeTitle": "Sentouin, Hakenshimasu!",
        "id": "combatants-will-be-dispatched-15539",
        "poster": "https://cdn.noitatnemucod.net/thumbnail/300x400/100/4d61af8dde6743da3d347e8596fb04e6.jpg",
        "episodes": {
          "sub": 12,
          "dub": 12,
          "eps": 12
        },
        "type": "TV",
        "duration": "24m"
      },
      {
        "title": "My Senpai is Annoying",
        "alternativeTitle": "Senpai ga Uzai Kouhai no Hanashi",
        "id": "my-senpai-is-annoying-15538",
        "poster": "https://cdn.noitatnemucod.net/thumbnail/300x400/100/4d3f2d68b022ba5e50b02f11648bd037.jpg",
        "episodes": {
          "sub": 12,
          "dub": 12,
          "eps": 12
        },
        "type": "TV",
        "duration": "23m"
      },
      {
        "title": "The Saint's Magic Power is Omnipotent",
        "alternativeTitle": "Seijo no Maryoku wa Bannou Desu",
        "id": "the-saints-magic-power-is-omnipotent-15536",
        "poster": "https://cdn.noitatnemucod.net/thumbnail/300x400/100/67a58ec87d387fc109a33af11a88f4bd.jpg",
        "episodes": {
          "sub": 12,
          "dub": 12,
          "eps": 12
        },
        "type": "TV",
        "duration": "23m"
      },
      {
        "title": "Sakugan Labyrinth Marker",
        "alternativeTitle": "Sacks&Guns!!",
        "id": "sakugan-labyrinth-marker-15533",
        "poster": "https://cdn.noitatnemucod.net/thumbnail/300x400/100/87eb0f3c79b21aaa2b3bc50870ae2e00.jpg",
        "episodes": {
          "sub": 12,
          "dub": 12,
          "eps": 12
        },
        "type": "TV",
        "duration": "24m"
      },
      {
        "title": "Ryoma! The Prince of Tennis",
        "alternativeTitle": "Ryouma! The Prince of Tennis Shinsei Movie: Tennis no Ouji-sama",
        "id": "ryoma-the-prince-of-tennis-15529",
        "poster": "https://cdn.noitatnemucod.net/thumbnail/300x400/100/f943659c438d1fda64e7a2aab9ac5fa1.jpg",
        "episodes": {
          "sub": 1,
          "dub": 1,
          "eps": 1
        },
        "type": "Movie",
        "duration": "100m"
      },
      {
        "title": "Re:Zero - Starting Life in Another World 2nd Season (Part 2)",
        "alternativeTitle": "Re:Zero kara Hajimeru Isekai Seikatsu 2nd Season Part 2",
        "id": "rezero-starting-life-in-another-world-2nd-season-part-2-15526",
        "poster": "https://cdn.noitatnemucod.net/thumbnail/300x400/100/b901e36b53189d739740f0e5edb96459.jpg",
        "episodes": {
          "sub": 12,
          "dub": 12,
          "eps": 12
        },
        "type": "TV",
        "duration": "28m"
      },
      {
        "title": "Scar on the Praeter",
        "alternativeTitle": "Project Scard: Praeter no Kizu",
        "id": "scar-on-the-praeter-15522",
        "poster": "https://cdn.noitatnemucod.net/thumbnail/300x400/100/3176cb3c1d77e56a18e3a989a9639b5a.jpg",
        "episodes": {
          "sub": 13,
          "dub": 13,
          "eps": 13
        },
        "type": "TV",
        "duration": "23m"
      },
      {
        "title": "Princess Principal Crown Handler Movie 1",
        "alternativeTitle": "Princess Principal: Crown Handler 1",
        "id": "princess-principal-crown-handler-movie-1-15521",
        "poster": "https://cdn.noitatnemucod.net/thumbnail/300x400/100/0dd0b03cadb8e424e623e6ef0b835109.jpg",
        "episodes": {
          "sub": 1,
          "dub": 1,
          "eps": 1
        },
        "type": "Movie",
        "duration": "53m"
      },
      {
        "title": "Pokemon Movie 23: Coco",
        "alternativeTitle": "Pokemon Movie 23: Coco",
        "id": "pokemon-movie-23-coco-15517",
        "poster": "https://cdn.noitatnemucod.net/thumbnail/300x400/100/c6b7fceb562c881fc5724046e35737c6.jpg",
        "episodes": {
          "sub": 1,
          "dub": 1,
          "eps": 1
        },
        "type": "Movie",
        "duration": "100m"
      }
    ]
  }
}